dtn7zero/__init__.py
dtn7zero/api.py
dtn7zero/bundle_protocol_agent.py
dtn7zero/configuration.py
dtn7zero/data.py
dtn7zero/endpoints.py
dtn7zero/ipnd.py
dtn7zero/utility.py
dtn7zero/convergence_layer_adapters/__init__.py
dtn7zero/convergence_layer_adapters/dtn7rs_rest.py
dtn7zero/convergence_layer_adapters/espnow_cla.py
dtn7zero/convergence_layer_adapters/mtcp.py
dtn7zero/routers/__init__.py
dtn7zero/routers/simple_epidemic_router.py
dtn7zero/storage/__init__.py
dtn7zero/storage/simple_in_memory_storage.py
dtn7zero-0.0.8.dist-info/LICENSE
dtn7zero-0.0.8.dist-info/METADATA
dtn7zero-0.0.8.dist-info/WHEEL
dtn7zero-0.0.8.dist-info/top_level.txt
dtn7zero-0.0.8.dist-info/RECORD
