Metadata-Version: 2.1
Name: dtn7zero
Version: 0.0.8
Author-email: Lukas Holst <lh700@proton.me>
License: AGPL-3.0
Project-URL: Homepage, https://github.com/dtn7/dtn7zero
Project-URL: Repository, https://github.com/dtn7/dtn7zero
Requires-Python: >=3.7
License-File: LICENSE
Requires-Dist: requests (>=2.27.1)
Requires-Dist: cbor2
Requires-Dist: netifaces
Requires-Dist: py-dtn7 (==0.3.0b1)
